README.md
setup.py
shtools/__init__.py
shtools.egg-info/PKG-INFO
shtools.egg-info/SOURCES.txt
shtools.egg-info/dependency_links.txt
shtools.egg-info/not-zip-safe
shtools.egg-info/requires.txt
shtools.egg-info/top_level.txt
shtools/bash/__init__.py
shtools/bash/abstract_cmd.py
shtools/bash/bash.py
shtools/bash/column.py
shtools/bash/curl.py
shtools/bash/jq.py
shtools/bash/kafkacli.py
shtools/bash/mongo.py
shtools/bash/mysql.py
shtools/bash/nc.py
shtools/bash/ntpdate.py
shtools/bash/ping.py
shtools/bash/psql.py
shtools/bash/rediscli.py
shtools/bash/scp.py
shtools/bash/ssh.py
shtools/utils/__init__.py
shtools/utils/cmdline.py
shtools/utils/log.py