Metadata-Version: 2.1
Name: shtools
Version: 2.2.2
Summary: some useful bash tools write in python
Home-page: https://github.com/meanstrong/shtools
Author: pengmingqiang
Author-email: rockypengchina@outlook.com
Maintainer: pengmingqiang
Maintainer-email: rockypengchina@outlook.com
License: Apache 2.0
Platform: any
Classifier: Programming Language :: Python :: 3
Classifier: Operating System :: OS Independent
Provides-Extra: curl
Provides-Extra: mongo
Provides-Extra: mysql
Provides-Extra: psql
Provides-Extra: rediscli
Provides-Extra: scp
Provides-Extra: ssh
Provides-Extra: kafka
